pyfcm/__init__.py
pyfcm/__meta__.py
pyfcm/async_fcm.py
pyfcm/baseapi.py
pyfcm/errors.py
pyfcm/fcm.py
pyfcm-2.0.9.dist-info/licenses/LICENSE
pyfcm-2.0.9.dist-info/METADATA
pyfcm-2.0.9.dist-info/WHEEL
pyfcm-2.0.9.dist-info/top_level.txt
pyfcm-2.0.9.dist-info/RECORD
